[
	{
		"path": "$ROOTPATH$\\div.map.js",
		"bookmarks": [
			{
				"line": 842,
				"column": 1,
				"label": "K"
			},
			{
				"line": 1101,
				"column": 4,
				"label": "K.map"
			},
			{
				"line": 1224,
				"column": 4,
				"label": "K.settings"
			},
			{
				"line": 1496,
				"column": 4,
				"label": "K.updateMarker()"
			},
			{
				"line": 1606,
				"column": 0,
				"label": "K.tool.marker"
			},
			{
				"line": 1797,
				"column": 0,
				"label": "K.tool.layer"
			},
			{
				"line": 2101,
				"column": 4,
				"label": "K.tool.layer._settingClick()"
			},
			{
				"line": 3522,
				"column": 0,
				"label": "Document Loaded"
			},
			{
				"line": 3808,
				"column": 0,
				"label": "pageLoad()"
			},
			{
				"line": 4082,
				"column": 0,
				"label": "Draw Events"
			},
			{
				"line": 4222,
				"column": 0,
				"label": "populateMap()"
			},
			{
				"line": 4444,
				"column": 0,
				"label": "populateMenus()"
			},
			{
				"line": 5014,
				"column": 0,
				"label": "drawEventCreated()"
			},
			{
				"line": 5360,
				"column": 0,
				"label": "createMarker()"
			},
			{
				"line": 5579,
				"column": 0,
				"label": "createGeoJSON()"
			}
		]
	},
	{
		"path": "$ROOTPATH$\\sass\\div.map.scss",
		"bookmarks": [
			{
				"line": 2621,
				"column": 6,
				"label": ""
			}
		]
	}
]